zucchini/__init__.py
zucchini/amazon.py
zucchini/assignment.py
zucchini/canvas.py
zucchini/cli.py
zucchini/constants.py
zucchini/export_manager.py
zucchini/farms.py
zucchini/filter.py
zucchini/flatten.py
zucchini/grades.py
zucchini/gradescope.py
zucchini/grading_manager.py
zucchini/local_grading.py
zucchini/submission.py
zucchini/utils.py
zucchini/zucchini.py
zucchini/exporters/__init__.py
zucchini/exporters/csv_exporter.py
zucchini/exporters/exporter_interface.py
zucchini/graders/__init__.py
zucchini/graders/bitwise_json_grader.py
zucchini/graders/circuitsim_grader.py
zucchini/graders/command_grader.py
zucchini/graders/criterion_grader.py
zucchini/graders/docker_wrapper_grader.py
zucchini/graders/ensemble_grader.py
zucchini/graders/exceptions.py
zucchini/graders/grader_interface.py
zucchini/graders/junit_json_grader.py
zucchini/graders/junit_xml_grader.py
zucchini/graders/lc3tools_grader.py
zucchini/graders/lc3tools_legacy_grader.py
zucchini/graders/libcheck_grader.py
zucchini/graders/multi_command_grader.py
zucchini/graders/open_file_grader.py
zucchini/graders/prompt_grader.py
zucchini/graders/pylc3_grader.py
zucchini/graders/python_module_grader.py
zucchini/graders/threaded_grader.py
zucchini/loaders/__init__.py
zucchini/loaders/canvas_archive_loader.py
zucchini/loaders/canvas_loader.py
zucchini/loaders/gradescope_loader.py
zucchini/loaders/sakai_loader.py
zucchini/penalizers/__init__.py
zucchini/penalizers/checkoff_penalizer.py
zucchini/penalizers/exceptions.py
zucchini/penalizers/late_penalizer.py
zucchini/penalizers/penalizer_interface.py
zucchini-2.2.21.dist-info/AUTHORS.rst
zucchini-2.2.21.dist-info/LICENSE
zucchini-2.2.21.dist-info/METADATA
zucchini-2.2.21.dist-info/WHEEL
zucchini-2.2.21.dist-info/entry_points.txt
zucchini-2.2.21.dist-info/top_level.txt
zucchini-2.2.21.dist-info/RECORD
