Metadata-Version: 2.1
Name: zucchini
Version: 2.2.21
Summary: Zucchini is an automatic grader tool for use in grading programming assignments.
Home-page: https://github.com/zucchini/zucchini
Author: Zucchini Team
Author-email: team@zucc.io
License: Apache Software License 2.0
Keywords: zucchini
Classifier: Development Status :: 2 - Pre-Alpha
Classifier: Intended Audience :: Developers
Classifier: License :: OSI Approved :: Apache Software License
Classifier: Natural Language :: English
Classifier: Programming Language :: Python :: 3
Classifier: Programming Language :: Python :: 3.4
Classifier: Programming Language :: Python :: 3.5
Classifier: Programming Language :: Python :: 3.6
Classifier: Programming Language :: Python :: 3.7
Classifier: Programming Language :: Python :: 3.8
License-File: LICENSE
License-File: AUTHORS.rst
Requires-Dist: click (==6.7)
Requires-Dist: gitdb2 (==2.0.3)
Requires-Dist: GitPython (==3.1.30)
Requires-Dist: PyYAML (==6.0.1)
Requires-Dist: smmap2 (==2.0.3)
Requires-Dist: requests (==2.28.2)
Requires-Dist: boto3 (==1.26.42)
Requires-Dist: arrow (==0.15.1)
Requires-Dist: subprocess32 (==3.2.7) ; python_version < "3.0"
